slamlab/__init__.py
slamlab-0.0.1.dist-info/licenses/LICENSE
slamlab-0.0.1.dist-info/METADATA
slamlab-0.0.1.dist-info/WHEEL
slamlab-0.0.1.dist-info/top_level.txt
slamlab-0.0.1.dist-info/RECORD
