Metadata-Version: 2.4
Name: slamlab
Version: 0.0.1
Summary: The SLAMLab Python Package
Author-email: SLAMLab <slamlabapp@gmail.com>
License: MIT
Project-URL: Homepage, https://github.com/SLAMLabApp/slamlab_python
Project-URL: Source, https://github.com/SLAMLabApp/slamlab_python
Keywords: SLAM,robotics,mapping,localization
Classifier: Programming Language :: Python :: 3
Classifier: License :: OSI Approved :: MIT License
Classifier: Operating System :: OS Independent
Classifier: Development Status :: 1 - Planning
Classifier: Intended Audience :: Developers
Classifier: Topic :: Software Development :: Libraries
Requires-Python: >=3.8
License-File: LICENSE
Dynamic: license-file
